<?xml version="1.0" encoding="utf-8"?>
<baseline version="1.0">
    <file name="src/main/java/com/digitalsolution/familyfilmapp/ui/components/RecommendedMovieCard.kt">
        <error line="34" column="5" source="compose:param-order-check" />
    </file>
    <file name="src/main/java/com/digitalsolution/familyfilmapp/ui/screens/login/LoginScreen.kt">
        <error column="5" line="127" source="compose:modifier-reused-check" />
        <error column="43" line="166" source="compose:remember-missing-check" />
        <error column="13" line="180" source="compose:modifier-reused-check" />
        <error column="17" line="181" source="compose:modifier-not-used-at-root" />
    </file>
    <file name="src/main/java/com/digitalsolution/familyfilmapp/ui/screens/login/components/DialogRecoverScreen.kt">
        <error line="49" column="21" source="compose:modifier-not-used-at-root" />
    </file>
    <file name="src/main/java/com/digitalsolution/familyfilmapp/ui/screens/login/components/LoginMainContent.kt">
        <error line="49" column="9" source="compose:modifier-reused-check" />
        <error line="50" column="13" source="compose:modifier-not-used-at-root" />
        <error line="55" column="13" source="compose:modifier-reused-check" />
        <error line="58" column="17" source="compose:modifier-not-used-at-root" />
        <error line="86" column="13" source="compose:modifier-reused-check" />
        <error line="86" column="20" source="compose:modifier-not-used-at-root" />
        <error line="88" column="13" source="compose:modifier-reused-check" />
        <error line="91" column="17" source="compose:modifier-not-used-at-root" />
        <error line="114" column="17" source="compose:modifier-reused-check" />
        <error line="116" column="21" source="compose:modifier-not-used-at-root" />
        <error line="118" column="21" source="compose:modifier-reused-check" />
        <error line="120" column="25" source="compose:modifier-not-used-at-root" />
        <error line="130" column="5" source="compose:modifier-reused-check" />
        <error line="132" column="13" source="compose:modifier-reused-check" />
        <error line="135" column="17" source="compose:modifier-not-used-at-root" />
    </file>
    <file name="src/main/java/com/digitalsolution/familyfilmapp/ui/theme/FFATheme.kt">
        <error column="5" line="9" source="compose:compositionlocal-allowlist" />
        <error column="5" line="13" source="compose:compositionlocal-allowlist" />
    </file>
</baseline>
